{
  "name": "Puerto Rico",
  "altSpellings": [
    "PR",
    "Commonwealth of Puerto Rico",
    "Estado Libre Asociado de Puerto Rico"
  ],
  "area": 8870,
  "borders": [],
  "callingCodes": ["1787", "1939"],
  "capital": "San Juan",
  "currencies": ["USD"],
  "demonym": "Puerto Rican",
  "flag": "",
  "geoJSON": {
    "type": "FeatureCollection",
    "features": [
      {
        "type": "Feature",
        "id": "PRI",
        "properties": { "name": "Puerto Rico" },
        "geometry": {
          "type": "Polygon",
          "coordinates": [
            [
              [-66.282434, 18.514762],
              [-65.771303, 18.426679],
              [-65.591004, 18.228035],
              [-65.847164, 17.975906],
              [-66.599934, 17.981823],
              [-67.184162, 17.946553],
              [-67.242428, 18.37446],
              [-67.100679, 18.520601],
              [-66.282434, 18.514762]
            ]
          ]
        }
      }
    ]
  },
  "ISO": { "alpha2": "PR", "alpha3": "PRI" },
  "languages": ["es", "en"],
  "latlng": [18.25, -66.5],
  "nativeName": "Puerto Rico",
  "population": 3615086,
  "region": "Americas",
  "subregion": "Caribbean",
  "timezones": null,
  "tld": [".pr"],
  "translations": {
    "de": "Puerto Rico",
    "es": "Puerto Rico",
    "fr": "Porto Rico",
    "ja": "プエルトリコ",
    "it": "Porto Rico"
  },
  "wiki": "http://en.wikipedia.org/wiki/puerto_rico",
  "states": [
    { "name": "Adjuntas", "abbreviation": "", "country": "PR" },
    { "name": "Aguada", "abbreviation": "", "country": "PR" },
    { "name": "Aguadilla", "abbreviation": "", "country": "PR" },
    { "name": "Aguas Buenas", "abbreviation": "", "country": "PR" },
    { "name": "Aibonito", "abbreviation": "", "country": "PR" },
    { "name": "Anasco", "abbreviation": "", "country": "PR" },
    { "name": "Arecibo", "abbreviation": "", "country": "PR" },
    { "name": "Arroyo", "abbreviation": "", "country": "PR" },
    { "name": "Barceloneta", "abbreviation": "", "country": "PR" },
    { "name": "Barranquitas", "abbreviation": "", "country": "PR" },
    { "name": "Bayamon", "abbreviation": "", "country": "PR" },
    { "name": "Cabo Rojo", "abbreviation": "", "country": "PR" },
    { "name": "Caguas", "abbreviation": "", "country": "PR" },
    { "name": "Camuy", "abbreviation": "", "country": "PR" },
    { "name": "Canovanas", "abbreviation": "", "country": "PR" },
    { "name": "Carolina", "abbreviation": "", "country": "PR" },
    { "name": "Catano", "abbreviation": "", "country": "PR" },
    { "name": "Cayey", "abbreviation": "", "country": "PR" },
    { "name": "Ceiba", "abbreviation": "", "country": "PR" },
    { "name": "Ciales", "abbreviation": "", "country": "PR" },
    { "name": "Cidra", "abbreviation": "", "country": "PR" },
    { "name": "Coamo", "abbreviation": "", "country": "PR" },
    { "name": "Comerio", "abbreviation": "", "country": "PR" },
    { "name": "Corozal", "abbreviation": "CZL", "country": "PR" },
    { "name": "Culebra", "abbreviation": "", "country": "PR" },
    { "name": "Dorado", "abbreviation": "", "country": "PR" },
    { "name": "Fajardo", "abbreviation": "", "country": "PR" },
    { "name": "Florida", "abbreviation": "FL", "country": "PR" },
    { "name": "Guanica", "abbreviation": "", "country": "PR" },
    { "name": "Guayama", "abbreviation": "", "country": "PR" },
    { "name": "Guayanilla", "abbreviation": "", "country": "PR" },
    { "name": "Guaynabo", "abbreviation": "", "country": "PR" },
    { "name": "Gurabo", "abbreviation": "", "country": "PR" },
    { "name": "Hatillo", "abbreviation": "", "country": "PR" },
    { "name": "Hormigueros", "abbreviation": "", "country": "PR" },
    { "name": "Humacao", "abbreviation": "", "country": "PR" },
    { "name": "Isabela", "abbreviation": "ISA", "country": "PR" },
    { "name": "Jayuya", "abbreviation": "", "country": "PR" },
    { "name": "Juana Diaz", "abbreviation": "", "country": "PR" },
    { "name": "Juncos", "abbreviation": "", "country": "PR" },
    { "name": "Lajas", "abbreviation": "", "country": "PR" },
    { "name": "Lares", "abbreviation": "", "country": "PR" },
    { "name": "Las Marias", "abbreviation": "", "country": "PR" },
    { "name": "Las Piedras", "abbreviation": "", "country": "PR" },
    { "name": "Loiza", "abbreviation": "", "country": "PR" },
    { "name": "Luquillo", "abbreviation": "", "country": "PR" },
    { "name": "Manati", "abbreviation": "", "country": "PR" },
    { "name": "Maricao", "abbreviation": "", "country": "PR" },
    { "name": "Maunabo", "abbreviation": "", "country": "PR" },
    { "name": "Mayaguez", "abbreviation": "", "country": "PR" },
    { "name": "Moca", "abbreviation": "", "country": "PR" },
    { "name": "Morovis", "abbreviation": "", "country": "PR" },
    { "name": "Naguabo", "abbreviation": "", "country": "PR" },
    { "name": "Naranjito", "abbreviation": "", "country": "PR" },
    { "name": "Orocovis", "abbreviation": "", "country": "PR" },
    { "name": "Patillas", "abbreviation": "", "country": "PR" },
    { "name": "Penuelas", "abbreviation": "", "country": "PR" },
    { "name": "Ponce", "abbreviation": "", "country": "PR" },
    { "name": "Quebradillas", "abbreviation": "", "country": "PR" },
    { "name": "Rincon", "abbreviation": "", "country": "PR" },
    { "name": "Rio Grande", "abbreviation": "", "country": "PR" },
    { "name": "Sabana Grande", "abbreviation": "", "country": "PR" },
    { "name": "Salinas", "abbreviation": "", "country": "PR" },
    { "name": "San German", "abbreviation": "", "country": "PR" },
    { "name": "San Juan", "abbreviation": "J", "country": "PR" },
    { "name": "San Lorenzo", "abbreviation": "", "country": "PR" },
    { "name": "San Sebastian", "abbreviation": "", "country": "PR" },
    { "name": "Santa Isabel", "abbreviation": "", "country": "PR" },
    { "name": "Toa Alta", "abbreviation": "", "country": "PR" },
    { "name": "Toa Baja", "abbreviation": "", "country": "PR" },
    { "name": "Trujillo Alto", "abbreviation": "", "country": "PR" },
    { "name": "Utuado", "abbreviation": "", "country": "PR" },
    { "name": "Vega Alta", "abbreviation": "", "country": "PR" },
    { "name": "Vega Baja", "abbreviation": "", "country": "PR" },
    { "name": "Vieques", "abbreviation": "", "country": "PR" },
    { "name": "Villalba", "abbreviation": "", "country": "PR" },
    { "name": "Yabucoa", "abbreviation": "", "country": "PR" },
    { "name": "Yauco", "abbreviation": "", "country": "PR" }
  ]
}
